yardstick/__init__.py
yardstick/arrange.py
yardstick/artifact.py
yardstick/capture.py
yardstick/comparison.py
yardstick/label.py
yardstick/cli/__init__.py
yardstick/cli/cli.py
yardstick/cli/config.py
yardstick/cli/display.py
yardstick/cli/label.py
yardstick/cli/result.py
yardstick/cli/validate.py
yardstick/cli/explore/__init__.py
yardstick/cli/explore/result.py
yardstick/cli/explore/image_labels/__init__.py
yardstick/cli/explore/image_labels/cve_provider.py
yardstick/cli/explore/image_labels/display_pane.py
yardstick/cli/explore/image_labels/edit_note_dialog.py
yardstick/cli/explore/image_labels/history.py
yardstick/cli/explore/image_labels/label_json_editor_dialog.py
yardstick/cli/explore/image_labels/label_manager.py
yardstick/cli/explore/image_labels/label_margin.py
yardstick/cli/explore/image_labels/label_selection_pane.py
yardstick/cli/explore/image_labels/result_selection_pane.py
yardstick/cli/explore/image_labels/text_area.py
yardstick/cli/explore/image_labels/text_dialog.py
yardstick/store/__init__.py
yardstick/store/config.py
yardstick/store/image_lineage.py
yardstick/store/label_stats.py
yardstick/store/labels.py
yardstick/store/naming.py
yardstick/store/result_set.py
yardstick/store/scan_result.py
yardstick/store/tool.py
yardstick/tool/__init__.py
yardstick/tool/grype.py
yardstick/tool/plugin.py
yardstick/tool/sbom_generator.py
yardstick/tool/syft.py
yardstick/tool/vulnerability_scanner.py
yardstick/utils/__init__.py
yardstick/utils/github.py
yardstick/utils/grype_db.py
yardstick/validate/__init__.py
yardstick/validate/delta.py
yardstick/validate/gate.py
yardstick/validate/validate.py
yardstick-0.15.0.dist-info/METADATA
yardstick-0.15.0.dist-info/WHEEL
yardstick-0.15.0.dist-info/entry_points.txt
yardstick-0.15.0.dist-info/licenses/LICENSE
yardstick-0.15.0.dist-info/RECORD
