Metadata-Version: 2.4
Name: yardstick
Version: 0.15.0
Summary: Tool for comparing the results from vulnerability scanners
Project-URL: repository, https://github.com/anchore/yardstick
Author-email: Alex Goodman <alex.goodman@anchore.com>
License: Apache 2.0
License-File: LICENSE
Keywords: grype,vulnerability
Classifier: Development Status :: 5 - Production/Stable
Classifier: Intended Audience :: Developers
Classifier: Intended Audience :: Information Technology
Classifier: Intended Audience :: System Administrators
Classifier: Natural Language :: English
Classifier: Operating System :: MacOS
Classifier: Operating System :: POSIX :: Linux
Classifier: Topic :: Security
Classifier: Topic :: Software Development :: Libraries :: Python Modules
Classifier: Topic :: Utilities
Requires-Python: <3.14,>=3.11
Requires-Dist: click<9,>=8
Requires-Dist: dataclass-wizard<1.0.0,>=0.30.1
Requires-Dist: dataclasses-json<1.0.0,>=0.6.7
Requires-Dist: gitpython<4.0.0,>=3.1.43
Requires-Dist: importlib-metadata<9.0.0,>=7.0.1
Requires-Dist: mergedeep<2.0.0,>=1.3.4
Requires-Dist: omitempty<1.0.0,>=0.1.1
Requires-Dist: prompt-toolkit<4.0.0,>=3.0.48
Requires-Dist: pygments<3.0.0,>=2.18.0
Requires-Dist: pyyaml<7.0,>=6.0.0
Requires-Dist: requests<3.0.0,>=2.32.3
Requires-Dist: tabulate<1.0.0,>=0.9.0
Requires-Dist: xxhash<4.0.0,>=3.5.0
Requires-Dist: zstandard<1.0.0,>=0.23.0
